LICENSE.txt
MANIFEST.in
README.md
setup.cfg
setup.py
bin/deep-blue-talks
deep_blue_talks.egg-info/PKG-INFO
deep_blue_talks.egg-info/SOURCES.txt
deep_blue_talks.egg-info/dependency_links.txt
deep_blue_talks.egg-info/not-zip-safe
deep_blue_talks.egg-info/pbr.json
deep_blue_talks.egg-info/requires.txt
deep_blue_talks.egg-info/top_level.txt
kasparobot/__init__.py
kasparobot/engines/stockfish