Metadata-Version: 1.1
Name: deep-blue-talks
Version: 0.2.2
Summary: bestow speech unto chess engines
Home-page: https://github.com/pcattori/deep-blue-talks
Author: Pedro Cattori
Author-email: pcattori@gmail.com
License: MIT
Keywords: deep blue talks chess pedro cattori
Platform: UNKNOWN
Classifier: Development Status :: 3 - Alpha
Classifier: License :: OSI Approved :: MIT License
Classifier: Natural Language :: English
Classifier: Programming Language :: Python :: 2.7
Classifier: Topic :: Scientific/Engineering :: Artificial Intelligence
Classifier: Topic :: Games/Entertainment :: Board Games
Classifier: Topic :: Software Development :: Libraries :: Python Modules
